{"id":39,"seed":"7bb15e65-bc85-4bcc-a153-03ba9be509c2","leader":"Zetune Mk XII","value":"0.808","drones":[{"seed":"7bb15e65-bc85-4bcc-a153-03ba9be509c2","name":"Zetune Mk XII","weapon":1,"gimbal":5,"steering":5,"thruster":4,"chassis":4,"scanner":4,"colour":2,"skewMod":"0.991","skew":6,"value":"0.917","weaponNormal":"0.667","thrusterNormal":"1.000","steeringNormal":"1.000","chassisNormal":"1.000","gimbalNormal":"1.000","scannerNormal":"0.833"},{"seed":"7bb15e65-bc85-4bcc-a153-03ba9be509c2","name":"Luzuno","weapon":0,"gimbal":5,"steering":4,"thruster":4,"chassis":3,"scanner":0,"colour":2,"skewMod":"0.920","skew":2.75,"value":"0.689","weaponNormal":"0.333","thrusterNormal":"1.000","steeringNormal":"0.833","chassisNormal":"0.800","gimbalNormal":"1.000","scannerNormal":"0.167"},{"seed":"7bb15e65-bc85-4bcc-a153-03ba9be509c2","name":"Laliv","weapon":2,"gimbal":0,"steering":5,"thruster":3,"chassis":3,"scanner":0,"colour":2,"skewMod":"0.176","skew":1,"value":"0.656","weaponNormal":"1.000","thrusterNormal":"0.800","steeringNormal":"1.000","chassisNormal":"0.800","gimbalNormal":"0.167","scannerNormal":"0.167"},{"seed":"7bb15e65-bc85-4bcc-a153-03ba9be509c2","name":"Motov","weapon":2,"gimbal":4,"steering":3,"thruster":1,"chassis":1,"scanner":2,"colour":2,"skewMod":"0.761","skew":1,"value":"0.633","weaponNormal":"1.000","thrusterNormal":"0.400","steeringNormal":"0.667","chassisNormal":"0.400","gimbalNormal":"0.833","scannerNormal":"0.500"},{"seed":"7bb15e65-bc85-4bcc-a153-03ba9be509c2","name":"Qolia v12.95","weapon":1,"gimbal":0,"steering":3,"thruster":4,"chassis":4,"scanner":0,"colour":2,"skewMod":"0.168","skew":1,"value":"0.611","weaponNormal":"0.667","thrusterNormal":"1.000","steeringNormal":"0.667","chassisNormal":"1.000","gimbalNormal":"0.167","scannerNormal":"0.167"},{"seed":"7bb15e65-bc85-4bcc-a153-03ba9be509c2","name":"Lophus Mk XXXI","weapon":0,"gimbal":4,"steering":3,"thruster":2,"chassis":2,"scanner":0,"colour":2,"skewMod":"0.531","skew":1,"value":"0.533","weaponNormal":"0.333","thrusterNormal":"0.600","steeringNormal":"0.667","chassisNormal":"0.600","gimbalNormal":"0.833","scannerNormal":"0.167"}]}