{"id":13,"seed":"b06f67cd-1cc5-415a-a9a4-5cb0901300d2","leader":"Relia","value":"0.779","drones":[{"seed":"b06f67cd-1cc5-415a-a9a4-5cb0901300d2","name":"Relia","weapon":2,"gimbal":5,"steering":5,"thruster":0,"chassis":4,"scanner":4,"colour":3,"skewMod":"0.955","skew":4,"value":"0.839","weaponNormal":"1.000","thrusterNormal":"0.200","steeringNormal":"1.000","chassisNormal":"1.000","gimbalNormal":"1.000","scannerNormal":"0.833"},{"seed":"b06f67cd-1cc5-415a-a9a4-5cb0901300d2","name":"Hewei v5.53","weapon":0,"gimbal":3,"steering":3,"thruster":3,"chassis":3,"scanner":5,"colour":3,"skewMod":"0.909","skew":2.75,"value":"0.711","weaponNormal":"0.333","thrusterNormal":"0.800","steeringNormal":"0.667","chassisNormal":"0.800","gimbalNormal":"0.667","scannerNormal":"1.000"},{"seed":"b06f67cd-1cc5-415a-a9a4-5cb0901300d2","name":"Getov v34.11","weapon":2,"gimbal":4,"steering":2,"thruster":3,"chassis":3,"scanner":0,"colour":3,"skewMod":"0.644","skew":1,"value":"0.683","weaponNormal":"1.000","thrusterNormal":"0.800","steeringNormal":"0.500","chassisNormal":"0.800","gimbalNormal":"0.833","scannerNormal":"0.167"},{"seed":"b06f67cd-1cc5-415a-a9a4-5cb0901300d2","name":"Dorus","weapon":2,"gimbal":4,"steering":1,"thruster":1,"chassis":4,"scanner":2,"colour":3,"skewMod":"0.876","skew":1.75,"value":"0.678","weaponNormal":"1.000","thrusterNormal":"0.400","steeringNormal":"0.333","chassisNormal":"1.000","gimbalNormal":"0.833","scannerNormal":"0.500"},{"seed":"b06f67cd-1cc5-415a-a9a4-5cb0901300d2","name":"Zonope","weapon":0,"gimbal":3,"steering":2,"thruster":3,"chassis":0,"scanner":3,"colour":3,"skewMod":"0.055","skew":0.5,"value":"0.528","weaponNormal":"0.333","thrusterNormal":"0.800","steeringNormal":"0.500","chassisNormal":"0.200","gimbalNormal":"0.667","scannerNormal":"0.667"},{"seed":"b06f67cd-1cc5-415a-a9a4-5cb0901300d2","name":"Danides","weapon":1,"gimbal":4,"steering":2,"thruster":0,"chassis":0,"scanner":1,"colour":3,"skewMod":"0.016","skew":0.15000000000000002,"value":"0.456","weaponNormal":"0.667","thrusterNormal":"0.200","steeringNormal":"0.500","chassisNormal":"0.200","gimbalNormal":"0.833","scannerNormal":"0.333"}]}